progress_text/ProgressText.py
progress_text/__init__.py
progress_text-0.0.5.dist-info/LICENSE
progress_text-0.0.5.dist-info/METADATA
progress_text-0.0.5.dist-info/WHEEL
progress_text-0.0.5.dist-info/top_level.txt
progress_text-0.0.5.dist-info/RECORD
