Metadata-Version: 2.1
Name: progress-text
Version: 0.0.5
Summary: Python package for printing progress in text.
Home-page: https://github.com/LinjianLi/progress-text
Author: Linjian Li
Author-email: author@example.com
License: UNKNOWN
Platform: UNKNOWN
Classifier: Programming Language :: Python :: 3
Classifier: License :: OSI Approved :: Apache Software License
Classifier: Operating System :: OS Independent
Requires-Python: >=3
